azureml/__init__.py
azureml/acft/__init__.py
azureml/acft/contrib/__init__.py
azureml/acft/contrib/hf/__init__.py
azureml/acft/contrib/hf/_version.py
azureml/acft/contrib/hf/nlp/NOTICE
azureml/acft/contrib/hf/nlp/__init__.py
azureml/acft/contrib/hf/nlp/base_runner.py
azureml/acft/contrib/hf/nlp/task_factory.py
azureml/acft/contrib/hf/nlp/constants/__init__.py
azureml/acft/contrib/hf/nlp/constants/constants.py
azureml/acft/contrib/hf/nlp/entry_point/__init__.py
azureml/acft/contrib/hf/nlp/entry_point/data_import/__init__.py
azureml/acft/contrib/hf/nlp/entry_point/data_import/data_import.py
azureml/acft/contrib/hf/nlp/entry_point/finetune/__init__.py
azureml/acft/contrib/hf/nlp/entry_point/finetune/finetune.py
azureml/acft/contrib/hf/nlp/entry_point/finetune/finetune_config.py
azureml/acft/contrib/hf/nlp/entry_point/finetune/model_selector.py
azureml/acft/contrib/hf/nlp/entry_point/finetune/preprocess.py
azureml/acft/contrib/hf/nlp/entry_point/finetune/register_model.py
azureml/acft/contrib/hf/nlp/entry_point/finetune/register_presets_model.py
azureml/acft/contrib/hf/nlp/entry_point/finetune/validate_lora_weights.py
azureml/acft/contrib/hf/nlp/entry_point/finetune/zero2.json
azureml/acft/contrib/hf/nlp/entry_point/finetune/zero3.json
azureml/acft/contrib/hf/nlp/metrics/__init__.py
azureml/acft/contrib/hf/nlp/metrics/load_metric.py
azureml/acft/contrib/hf/nlp/metrics/rouge.py
azureml/acft/contrib/hf/nlp/metrics/sacrebleu.py
azureml/acft/contrib/hf/nlp/nlp_auto/__init__.py
azureml/acft/contrib/hf/nlp/nlp_auto/config.py
azureml/acft/contrib/hf/nlp/nlp_auto/model.py
azureml/acft/contrib/hf/nlp/nlp_auto/tokenizer.py
azureml/acft/contrib/hf/nlp/tasks/__init__.py
azureml/acft/contrib/hf/nlp/tasks/base/__init__.py
azureml/acft/contrib/hf/nlp/tasks/base/finetune/__init__.py
azureml/acft/contrib/hf/nlp/tasks/base/finetune/finetune.py
azureml/acft/contrib/hf/nlp/tasks/multi_label/__init__.py
azureml/acft/contrib/hf/nlp/tasks/multi_label/runner.py
azureml_acft_contrib_hf_nlp-47.0.0.dist-info/LICENSE.txt
azureml_acft_contrib_hf_nlp-47.0.0.dist-info/METADATA
azureml_acft_contrib_hf_nlp-47.0.0.dist-info/WHEEL
azureml_acft_contrib_hf_nlp-47.0.0.dist-info/top_level.txt
azureml_acft_contrib_hf_nlp-47.0.0.dist-info/RECORD
