Metadata-Version: 2.1
Name: azureml-acft-contrib-hf-nlp
Version: 47.0.0
Summary: Contains the acft nlp-hf-contrib package used in script to build azureml components.
Home-page: 
Author: Microsoft Corp
License: inline_license
Classifier: Development Status :: 3 - Alpha
Classifier: Intended Audience :: Developers
Classifier: Intended Audience :: Science/Research
Classifier: License :: Other/Proprietary License
Classifier: Programming Language :: Python :: 3.7
Classifier: Programming Language :: Python :: 3.8
Classifier: Programming Language :: Python :: 3.9
Classifier: Programming Language :: Python :: 3.10
Classifier: Programming Language :: Python :: 3.11
Classifier: Topic :: Scientific/Engineering :: Artificial Intelligence
Classifier: Operating System :: Microsoft :: Windows
Classifier: Operating System :: MacOS
Classifier: Operating System :: POSIX :: Linux
Requires-Python: >=3.7,<3.12
License-File: LICENSE.txt
Requires-Dist: datasets >=2.3.2
Requires-Dist: sacremoses ==0.0.53
Requires-Dist: scikit-learn <=1.1.0,>=1.0.0
Requires-Dist: seqeval ==1.2.2
Provides-Extra: dev
Requires-Dist: twine ==3.3.0 ; extra == 'dev'
Requires-Dist: wheel ==0.37.0 ; extra == 'dev'
Provides-Extra: test
Requires-Dist: pytest ~=5.3.0 ; extra == 'test'
